{
  "users": [
    {
      "sip": "19301103 195903 1 01712",
      "nama": "Chan Can",
      "email": "json1@server",
      "password": "1234",
      "gender": "L",
      "tingkat": "1",
      "spesialis": "Jant",
      "jadwal": "Senin - Minggu, 08.00-20.00 WIB",
      "str": "1821303554327688",
      "id": 1
    }
  ],
  "dokter": [
    {
      "sip": "19301103 195903 1 01712",
      "nama": "Trisna Chandra",
      "gender": "L",
      "spesialis": "Mata",
      "jadwal": "Senin - Minggu, 08.00-20.00 WIB",
      "str": "1821303554327688",
      "id": 1
    },
    {
      "sip": "19301103 195903 1 01712",
      "nama": "Trisna Chandra",
      "gender": "L",
      "spesialis": "Mata",
      "jadwal": "Senin - Minggu, 08.00-20.00 WIB",
      "str": "1821303554327688",
      "id": 2
    }
  ],
  "patients": [
    {
      "nik": "3507131606000004",
      "name": "Mochammad Syafiuddin",
      "address": "4517 Washington Ave. Manchester, Kentucky 39495",
      "gender": "P",
      "phone": "(406) 555-0120",
      "placeOfBirth": "New York",
      "dateOfBirth": "2022-06-15",
      "disease": "",
      "handling": "",
      "jadwalRawat": "2022-06-17",
      "noAntri": "",
      "ketRawat": "Asam Lambung sembuh",
      "id": 1
    },
    {
      "nik": "3507131606000004",
      "name": "Jane Cooper",
      "address": "4517 Washington Ave. Manchester, Kentucky 39495",
      "gender": "P",
      "phone": "(406) 555-0120",
      "placeOfBirth": "New York",
      "dateOfBirth": "2022-06-15",
      "disease": "Gigi",
      "handling": "Rawat Jalan",
      "jadwalRawat": "2022-06-01",
      "noAntri": "",
      "ketRawat": "Komplikasi Jantung",
      "id": 2
    },
    {
      "nik": "3507131606000004",
      "name": "Ainun Rizki Abdillah",
      "address": "4517 Washington Ave. Manchester, Kentucky 39495",
      "gender": "P",
      "phone": "(406) 555-0120",
      "placeOfBirth": "New York",
      "dateOfBirth": "2022-06-15",
      "disease": "",
      "handling": "",
      "jadwalRawat": "2022-06-15",
      "noAntri": "",
      "ketRawat": "",
      "id": 3
    },
    {
      "nik": "3507131606000004",
      "name": "Maria Imaculata",
      "address": "Jl. Sultan Agung 46 RT.06 RW.03 Kepanjen Malang",
      "gender": "P",
      "phone": "089698289699",
      "placeOfBirth": "New York",
      "dateOfBirth": "2022-06-15",
      "disease": "",
      "handling": "",
      "jadwalRawat": "2022-07-01",
      "noAntri": "",
      "ketRawat": "",
      "id": 4
    },
    {
      "id": 5,
      "nik": "3507131606000004",
      "name": "Hedara Putri",
      "address": "Jl. Sultan Agung 46 RT.06 RW.03 Kepanjen Malang",
      "gender": "P",
      "phone": "089698289699",
      "placeOfBirth": "New York",
      "dateOfBirth": "2022-06-15",
      "disease": "",
      "handling": "",
      "jadwalRawat": "",
      "noAntri": "",
      "ketRawat": ""
    },
    {
      "id": 6,
      "nik": "3507131606000004",
      "name": "Alvindo Tri Jatmiko",
      "address": "4517 Washington Ave. Manchester, Kentucky 39495",
      "gender": "L",
      "phone": "(406) 555-0120",
      "placeOfBirth": "New York",
      "dateOfBirth": "2022-06-15",
      "disease": "",
      "handling": "",
      "jadwalRawat": "",
      "noAntri": "",
      "ketRawat": ""
    },
    {
      "id": 7,
      "nik": "3507131606000004",
      "name": "Abdul Malik Siddiq",
      "address": "4517 Washington Ave. Manchester, Kentucky 39495",
      "gender": "L",
      "phone": "(406) 555-0120",
      "placeOfBirth": "New York",
      "dateOfBirth": "2022-06-15",
      "disease": "",
      "handling": "",
      "jadwalRawat": "",
      "noAntri": "",
      "ketRawat": ""
    },
    {
      "id": 8,
      "nik": "3507131606000004",
      "name": "Rizki Firmansyah",
      "address": "Jl. Sultan Agung 46 RT.06 RW.03 Kepanjen Malang",
      "gender": "L",
      "phone": "089698289699",
      "placeOfBirth": "New York",
      "dateOfBirth": "2022-06-15",
      "disease": "",
      "handling": "",
      "jadwalRawat": "",
      "noAntri": "",
      "ketRawat": ""
    },
    {
      "id": 9,
      "nik": "3507131606000004",
      "name": "Fadwa Nazirah",
      "address": "Jl. Sultan Agung 46 RT.06 RW.03 Kepanjen Malang",
      "gender": "P",
      "phone": "089698289699",
      "placeOfBirth": "New York",
      "dateOfBirth": "2022-06-15",
      "disease": "",
      "handling": "",
      "jadwalRawat": "",
      "noAntri": "",
      "ketRawat": ""
    },
    {
      "id": 10,
      "nik": "3507131606000004",
      "name": "Yudha Pamungkas",
      "address": "4517 Washington Ave. Manchester, Kentucky 39495",
      "gender": "L",
      "phone": "(406) 555-0120",
      "placeOfBirth": "New York",
      "dateOfBirth": "2022-06-15",
      "disease": "",
      "handling": "",
      "jadwalRawat": "",
      "noAntri": "",
      "ketRawat": ""
    },
    {
      "id": 11,
      "nik": "3507131606000004",
      "name": "Andiny Nabila",
      "address": "4517 Washington Ave. Manchester, Kentucky 39495",
      "gender": "L",
      "phone": "(406) 555-0120",
      "placeOfBirth": "New York",
      "dateOfBirth": "2022-06-15",
      "disease": "",
      "handling": "",
      "jadwalRawat": "",
      "noAntri": "",
      "ketRawat": ""
    },
    {
      "nik": "3507131606000004",
      "name": "Sonia Istabella",
      "address": "4517 Washington Ave. Manchester, Kentucky 39495",
      "gender": "L",
      "phone": "(406) 555-0120",
      "placeOfBirth": "New York",
      "dateOfBirth": "2022-06-15",
      "disease": "",
      "handling": "",
      "id": 12,
      "jadwalRawat": "",
      "noAntri": "",
      "ketRawat": ""
    },
    {
      "nik": "3507131606000004",
      "name": "Fahmi Adin",
      "address": "4517 Washington Ave. Manchester, Kentucky 39495",
      "gender": "L",
      "phone": "(406) 555-0120",
      "placeOfBirth": "New York",
      "dateOfBirth": "2022-06-15",
      "disease": "",
      "handling": "",
      "id": 13,
      "jadwalRawat": "",
      "noAntri": "",
      "ketRawat": ""
    },
    {
      "nik": "3507131606000004",
      "name": "Roisul Umam",
      "address": "4517 Washington Ave. Manchester, Kentucky 39495",
      "gender": "L",
      "phone": "(406) 555-0120",
      "placeOfBirth": "New York",
      "dateOfBirth": "2022-06-15",
      "disease": "",
      "handling": "",
      "id": 14,
      "jadwalRawat": "",
      "noAntri": "",
      "ketRawat": ""
    },
    {
      "nik": "3507131606000004",
      "name": "Wahyu Pradana",
      "address": "4517 Washington Ave. Manchester, Kentucky 39495",
      "gender": "L",
      "phone": "(406) 555-0120",
      "placeOfBirth": "New York",
      "dateOfBirth": "2022-06-15",
      "disease": "",
      "handling": "",
      "id": 15,
      "jadwalRawat": "",
      "noAntri": "",
      "ketRawat": ""
    }
  ]
}